pypglib/__init__.py
pypglib/hvdc/CHANGELOG.md
pypglib/hvdc/LICENSE
pypglib/hvdc/MODEL.pdf
pypglib/hvdc/MODEL.tex
pypglib/hvdc/README.md
pypglib/hvdc/case24_7_jb.m
pypglib/hvdc/case3120_5_he.m
pypglib/hvdc/case39_10_he.m
pypglib/hvdc/case5_3_he.m
pypglib/hvdc/case67.m
pypglib/hvdc/nem_2000bus_hvdc.m
pypglib/opf/BASELINE.md
pypglib/opf/CHANGELOG.md
pypglib/opf/LICENSE
pypglib/opf/MODEL.png
pypglib/opf/MODEL.tex
pypglib/opf/README.md
pypglib/opf/pglib_opf_case10000_goc.m
pypglib/opf/pglib_opf_case10192_epigrids.m
pypglib/opf/pglib_opf_case10480_goc.m
pypglib/opf/pglib_opf_case118_ieee.m
pypglib/opf/pglib_opf_case1354_pegase.m
pypglib/opf/pglib_opf_case13659_pegase.m
pypglib/opf/pglib_opf_case14_ieee.m
pypglib/opf/pglib_opf_case162_ieee_dtc.m
pypglib/opf/pglib_opf_case179_goc.m
pypglib/opf/pglib_opf_case1803_snem.m
pypglib/opf/pglib_opf_case1888_rte.m
pypglib/opf/pglib_opf_case19402_goc.m
pypglib/opf/pglib_opf_case1951_rte.m
pypglib/opf/pglib_opf_case197_snem.m
pypglib/opf/pglib_opf_case2000_goc.m
pypglib/opf/pglib_opf_case200_activ.m
pypglib/opf/pglib_opf_case20758_epigrids.m
pypglib/opf/pglib_opf_case2312_goc.m
pypglib/opf/pglib_opf_case2383wp_k.m
pypglib/opf/pglib_opf_case240_pserc.m
pypglib/opf/pglib_opf_case24464_goc.m
pypglib/opf/pglib_opf_case24_ieee_rts.m
pypglib/opf/pglib_opf_case2736sp_k.m
pypglib/opf/pglib_opf_case2737sop_k.m
pypglib/opf/pglib_opf_case2742_goc.m
pypglib/opf/pglib_opf_case2746wop_k.m
pypglib/opf/pglib_opf_case2746wp_k.m
pypglib/opf/pglib_opf_case2848_rte.m
pypglib/opf/pglib_opf_case2853_sdet.m
pypglib/opf/pglib_opf_case2868_rte.m
pypglib/opf/pglib_opf_case2869_pegase.m
pypglib/opf/pglib_opf_case30000_goc.m
pypglib/opf/pglib_opf_case300_ieee.m
pypglib/opf/pglib_opf_case3012wp_k.m
pypglib/opf/pglib_opf_case3022_goc.m
pypglib/opf/pglib_opf_case30_as.m
pypglib/opf/pglib_opf_case30_ieee.m
pypglib/opf/pglib_opf_case3120sp_k.m
pypglib/opf/pglib_opf_case3375wp_k.m
pypglib/opf/pglib_opf_case3970_goc.m
pypglib/opf/pglib_opf_case39_epri.m
pypglib-0.0.3.dist-info/LICENSE
pypglib-0.0.3.dist-info/METADATA
pypglib-0.0.3.dist-info/WHEEL
pypglib-0.0.3.dist-info/top_level.txt
pypglib-0.0.3.dist-info/RECORD
