Metadata-Version: 2.1
Name: pypglib
Version: 0.0.3
Summary: PyPGLib: A Python Package for Easy Access to Power Grid Lib Benchmark
Author-email: Muhammad Yasirroni <muhammadyasirroni@gmail.com>
Maintainer-email: Muhammad Yasirroni <muhammadyasirroni@gmail.com>
Project-URL: Documentation, https://github.com/yasirroni/PyPGLib#readme
Project-URL: Issues, https://github.com/yasirroni/PyPGLib/issues
Project-URL: Source, https://github.com/yasirroni/PyPGLib
Classifier: Programming Language :: Python
Classifier: Programming Language :: Python :: 3.7
Classifier: Programming Language :: Python :: 3.8
Classifier: Programming Language :: Python :: 3.9
Classifier: Programming Language :: Python :: 3.10
Classifier: Programming Language :: Python :: 3.10
Classifier: Topic :: Scientific/Engineering
Classifier: Topic :: Scientific/Engineering :: Mathematics
Requires-Python: >=3.7.1
License-File: LICENSE
Provides-Extra: dev
Requires-Dist: pytest >=7.2.0 ; extra == 'dev'
Requires-Dist: pytest-cov >=4.0.0 ; extra == 'dev'
Requires-Dist: pytest-xdist >=3.1.0 ; extra == 'dev'
Requires-Dist: pre-commit >=2.21.0 ; extra == 'dev'
Requires-Dist: ruff >=0.6.8 ; extra == 'dev'
